<annotation>
        <folder>FOLDER</folder>
        <filename>000462567.jpg</filename>
        <path>data/scenes/val/000462567.jpg</path>
        <source>
                <database>Unknown</database>
        </source>
        <size>
                <width>720</width>
                <height>720</height>
                <depth>3</depth>
        </size>
 <object>
                <name>7h</name>
                <pose>Unspecified</pose>
                <truncated>0</truncated>
                <difficult>0</difficult>
                <bndbox>
                        <xmin>311</xmin>
                        <ymin>458</ymin>
                        <xmax>405</xmax>
                        <ymax>497</ymax>
                </bndbox>
        </object>
 <object>
                <name>7h</name>
                <pose>Unspecified</pose>
                <truncated>0</truncated>
                <difficult>0</difficult>
                <bndbox>
                        <xmin>443</xmin>
                        <ymin>355</ymin>
                        <xmax>535</xmax>
                        <ymax>394</ymax>
                </bndbox>
        </object>
 <object>
                <name>6s</name>
                <pose>Unspecified</pose>
                <truncated>0</truncated>
                <difficult>0</difficult>
                <bndbox>
                        <xmin>350</xmin>
                        <ymin>97</ymin>
                        <xmax>489</xmax>
                        <ymax>185</ymax>
                </bndbox>
        </object>
 <object>
                <name>6s</name>
                <pose>Unspecified</pose>
                <truncated>0</truncated>
                <difficult>0</difficult>
                <bndbox>
                        <xmin>250</xmin>
                        <ymin>334</ymin>
                        <xmax>388</xmax>
                        <ymax>419</ymax>
                </bndbox>
        </object>
</annotation>        
