<annotation>
        <folder>FOLDER</folder>
        <filename>021683354.jpg</filename>
        <path>data/scenes/val/021683354.jpg</path>
        <source>
                <database>Unknown</database>
        </source>
        <size>
                <width>720</width>
                <height>720</height>
                <depth>3</depth>
        </size>
 <object>
                <name>6d</name>
                <pose>Unspecified</pose>
                <truncated>0</truncated>
                <difficult>0</difficult>
                <bndbox>
                        <xmin>202</xmin>
                        <ymin>417</ymin>
                        <xmax>319</xmax>
                        <ymax>525</ymax>
                </bndbox>
        </object>
 <object>
                <name>Ac</name>
                <pose>Unspecified</pose>
                <truncated>0</truncated>
                <difficult>0</difficult>
                <bndbox>
                        <xmin>278</xmin>
                        <ymin>372</ymin>
                        <xmax>371</xmax>
                        <ymax>499</ymax>
                </bndbox>
        </object>
 <object>
                <name>9d</name>
                <pose>Unspecified</pose>
                <truncated>0</truncated>
                <difficult>0</difficult>
                <bndbox>
                        <xmin>337</xmin>
                        <ymin>351</ymin>
                        <xmax>424</xmax>
                        <ymax>486</ymax>
                </bndbox>
        </object>
 <object>
                <name>9d</name>
                <pose>Unspecified</pose>
                <truncated>0</truncated>
                <difficult>0</difficult>
                <bndbox>
                        <xmin>582</xmin>
                        <ymin>455</ymin>
                        <xmax>666</xmax>
                        <ymax>588</ymax>
                </bndbox>
        </object>
</annotation>        
