<annotation>
        <folder>FOLDER</folder>
        <filename>038258333.jpg</filename>
        <path>data/scenes/val/038258333.jpg</path>
        <source>
                <database>Unknown</database>
        </source>
        <size>
                <width>720</width>
                <height>720</height>
                <depth>3</depth>
        </size>
 <object>
                <name>Kh</name>
                <pose>Unspecified</pose>
                <truncated>0</truncated>
                <difficult>0</difficult>
                <bndbox>
                        <xmin>433</xmin>
                        <ymin>328</ymin>
                        <xmax>490</xmax>
                        <ymax>421</ymax>
                </bndbox>
        </object>
 <object>
                <name>Kh</name>
                <pose>Unspecified</pose>
                <truncated>0</truncated>
                <difficult>0</difficult>
                <bndbox>
                        <xmin>385</xmin>
                        <ymin>166</ymin>
                        <xmax>443</xmax>
                        <ymax>257</ymax>
                </bndbox>
        </object>
 <object>
                <name>9s</name>
                <pose>Unspecified</pose>
                <truncated>0</truncated>
                <difficult>0</difficult>
                <bndbox>
                        <xmin>59</xmin>
                        <ymin>288</ymin>
                        <xmax>138</xmax>
                        <ymax>367</ymax>
                </bndbox>
        </object>
 <object>
                <name>9s</name>
                <pose>Unspecified</pose>
                <truncated>0</truncated>
                <difficult>0</difficult>
                <bndbox>
                        <xmin>228</xmin>
                        <ymin>295</ymin>
                        <xmax>305</xmax>
                        <ymax>374</ymax>
                </bndbox>
        </object>
</annotation>        
