<annotation>
        <folder>FOLDER</folder>
        <filename>153020395.jpg</filename>
        <path>data/scenes/val/153020395.jpg</path>
        <source>
                <database>Unknown</database>
        </source>
        <size>
                <width>720</width>
                <height>720</height>
                <depth>3</depth>
        </size>
 <object>
                <name>9c</name>
                <pose>Unspecified</pose>
                <truncated>0</truncated>
                <difficult>0</difficult>
                <bndbox>
                        <xmin>307</xmin>
                        <ymin>215</ymin>
                        <xmax>447</xmax>
                        <ymax>295</ymax>
                </bndbox>
        </object>
 <object>
                <name>7h</name>
                <pose>Unspecified</pose>
                <truncated>0</truncated>
                <difficult>0</difficult>
                <bndbox>
                        <xmin>126</xmin>
                        <ymin>450</ymin>
                        <xmax>217</xmax>
                        <ymax>509</ymax>
                </bndbox>
        </object>
 <object>
                <name>7h</name>
                <pose>Unspecified</pose>
                <truncated>0</truncated>
                <difficult>0</difficult>
                <bndbox>
                        <xmin>290</xmin>
                        <ymin>407</ymin>
                        <xmax>380</xmax>
                        <ymax>465</ymax>
                </bndbox>
        </object>
</annotation>        
