<annotation>
        <folder>FOLDER</folder>
        <filename>160974556.jpg</filename>
        <path>data/scenes/val/160974556.jpg</path>
        <source>
                <database>Unknown</database>
        </source>
        <size>
                <width>720</width>
                <height>720</height>
                <depth>3</depth>
        </size>
 <object>
                <name>2c</name>
                <pose>Unspecified</pose>
                <truncated>0</truncated>
                <difficult>0</difficult>
                <bndbox>
                        <xmin>373</xmin>
                        <ymin>503</ymin>
                        <xmax>489</xmax>
                        <ymax>616</ymax>
                </bndbox>
        </object>
 <object>
                <name>Jd</name>
                <pose>Unspecified</pose>
                <truncated>0</truncated>
                <difficult>0</difficult>
                <bndbox>
                        <xmin>395</xmin>
                        <ymin>180</ymin>
                        <xmax>471</xmax>
                        <ymax>255</ymax>
                </bndbox>
        </object>
 <object>
                <name>Jd</name>
                <pose>Unspecified</pose>
                <truncated>0</truncated>
                <difficult>0</difficult>
                <bndbox>
                        <xmin>392</xmin>
                        <ymin>347</ymin>
                        <xmax>468</xmax>
                        <ymax>421</ymax>
                </bndbox>
        </object>
</annotation>        
