<annotation>
        <folder>FOLDER</folder>
        <filename>165256112.jpg</filename>
        <path>data/scenes/val/165256112.jpg</path>
        <source>
                <database>Unknown</database>
        </source>
        <size>
                <width>720</width>
                <height>720</height>
                <depth>3</depth>
        </size>
 <object>
                <name>7h</name>
                <pose>Unspecified</pose>
                <truncated>0</truncated>
                <difficult>0</difficult>
                <bndbox>
                        <xmin>443</xmin>
                        <ymin>130</ymin>
                        <xmax>584</xmax>
                        <ymax>193</ymax>
                </bndbox>
        </object>
 <object>
                <name>7h</name>
                <pose>Unspecified</pose>
                <truncated>0</truncated>
                <difficult>0</difficult>
                <bndbox>
                        <xmin>283</xmin>
                        <ymin>338</ymin>
                        <xmax>422</xmax>
                        <ymax>400</ymax>
                </bndbox>
        </object>
 <object>
                <name>4s</name>
                <pose>Unspecified</pose>
                <truncated>0</truncated>
                <difficult>0</difficult>
                <bndbox>
                        <xmin>256</xmin>
                        <ymin>162</ymin>
                        <xmax>352</xmax>
                        <ymax>201</ymax>
                </bndbox>
        </object>
 <object>
                <name>4s</name>
                <pose>Unspecified</pose>
                <truncated>0</truncated>
                <difficult>0</difficult>
                <bndbox>
                        <xmin>144</xmin>
                        <ymin>284</ymin>
                        <xmax>238</xmax>
                        <ymax>322</ymax>
                </bndbox>
        </object>
</annotation>        
