<annotation>
        <folder>FOLDER</folder>
        <filename>177550004.jpg</filename>
        <path>data/scenes/val/177550004.jpg</path>
        <source>
                <database>Unknown</database>
        </source>
        <size>
                <width>720</width>
                <height>720</height>
                <depth>3</depth>
        </size>
 <object>
                <name>7c</name>
                <pose>Unspecified</pose>
                <truncated>0</truncated>
                <difficult>0</difficult>
                <bndbox>
                        <xmin>412</xmin>
                        <ymin>392</ymin>
                        <xmax>488</xmax>
                        <ymax>478</ymax>
                </bndbox>
        </object>
 <object>
                <name>Qc</name>
                <pose>Unspecified</pose>
                <truncated>0</truncated>
                <difficult>0</difficult>
                <bndbox>
                        <xmin>386</xmin>
                        <ymin>368</ymin>
                        <xmax>470</xmax>
                        <ymax>442</ymax>
                </bndbox>
        </object>
 <object>
                <name>10d</name>
                <pose>Unspecified</pose>
                <truncated>0</truncated>
                <difficult>0</difficult>
                <bndbox>
                        <xmin>365</xmin>
                        <ymin>336</ymin>
                        <xmax>454</xmax>
                        <ymax>392</ymax>
                </bndbox>
        </object>
 <object>
                <name>10d</name>
                <pose>Unspecified</pose>
                <truncated>0</truncated>
                <difficult>0</difficult>
                <bndbox>
                        <xmin>421</xmin>
                        <ymin>179</ymin>
                        <xmax>510</xmax>
                        <ymax>233</ymax>
                </bndbox>
        </object>
</annotation>        
