<annotation>
        <folder>FOLDER</folder>
        <filename>203600718.jpg</filename>
        <path>data/scenes/val/203600718.jpg</path>
        <source>
                <database>Unknown</database>
        </source>
        <size>
                <width>720</width>
                <height>720</height>
                <depth>3</depth>
        </size>
 <object>
                <name>9h</name>
                <pose>Unspecified</pose>
                <truncated>0</truncated>
                <difficult>0</difficult>
                <bndbox>
                        <xmin>379</xmin>
                        <ymin>113</ymin>
                        <xmax>517</xmax>
                        <ymax>184</ymax>
                </bndbox>
        </object>
 <object>
                <name>9h</name>
                <pose>Unspecified</pose>
                <truncated>0</truncated>
                <difficult>0</difficult>
                <bndbox>
                        <xmin>150</xmin>
                        <ymin>223</ymin>
                        <xmax>285</xmax>
                        <ymax>294</ymax>
                </bndbox>
        </object>
 <object>
                <name>2h</name>
                <pose>Unspecified</pose>
                <truncated>0</truncated>
                <difficult>0</difficult>
                <bndbox>
                        <xmin>414</xmin>
                        <ymin>438</ymin>
                        <xmax>506</xmax>
                        <ymax>483</ymax>
                </bndbox>
        </object>
 <object>
                <name>2h</name>
                <pose>Unspecified</pose>
                <truncated>0</truncated>
                <difficult>0</difficult>
                <bndbox>
                        <xmin>558</xmin>
                        <ymin>355</ymin>
                        <xmax>648</xmax>
                        <ymax>400</ymax>
                </bndbox>
        </object>
</annotation>        
