<annotation>
        <folder>FOLDER</folder>
        <filename>222412081.jpg</filename>
        <path>data/scenes/val/222412081.jpg</path>
        <source>
                <database>Unknown</database>
        </source>
        <size>
                <width>720</width>
                <height>720</height>
                <depth>3</depth>
        </size>
 <object>
                <name>Ad</name>
                <pose>Unspecified</pose>
                <truncated>0</truncated>
                <difficult>0</difficult>
                <bndbox>
                        <xmin>323</xmin>
                        <ymin>241</ymin>
                        <xmax>402</xmax>
                        <ymax>305</ymax>
                </bndbox>
        </object>
 <object>
                <name>Ad</name>
                <pose>Unspecified</pose>
                <truncated>0</truncated>
                <difficult>0</difficult>
                <bndbox>
                        <xmin>362</xmin>
                        <ymin>210</ymin>
                        <xmax>428</xmax>
                        <ymax>286</ymax>
                </bndbox>
        </object>
 <object>
                <name>Qc</name>
                <pose>Unspecified</pose>
                <truncated>0</truncated>
                <difficult>0</difficult>
                <bndbox>
                        <xmin>411</xmin>
                        <ymin>180</ymin>
                        <xmax>472</xmax>
                        <ymax>273</ymax>
                </bndbox>
        </object>
 <object>
                <name>Qc</name>
                <pose>Unspecified</pose>
                <truncated>0</truncated>
                <difficult>0</difficult>
                <bndbox>
                        <xmin>570</xmin>
                        <ymin>245</ymin>
                        <xmax>629</xmax>
                        <ymax>338</ymax>
                </bndbox>
        </object>
</annotation>        
