<annotation>
        <folder>FOLDER</folder>
        <filename>274495959.jpg</filename>
        <path>data/scenes/val/274495959.jpg</path>
        <source>
                <database>Unknown</database>
        </source>
        <size>
                <width>720</width>
                <height>720</height>
                <depth>3</depth>
        </size>
 <object>
                <name>3c</name>
                <pose>Unspecified</pose>
                <truncated>0</truncated>
                <difficult>0</difficult>
                <bndbox>
                        <xmin>484</xmin>
                        <ymin>252</ymin>
                        <xmax>626</xmax>
                        <ymax>315</ymax>
                </bndbox>
        </object>
 <object>
                <name>4d</name>
                <pose>Unspecified</pose>
                <truncated>0</truncated>
                <difficult>0</difficult>
                <bndbox>
                        <xmin>470</xmin>
                        <ymin>313</ymin>
                        <xmax>612</xmax>
                        <ymax>367</ymax>
                </bndbox>
        </object>
 <object>
                <name>4s</name>
                <pose>Unspecified</pose>
                <truncated>0</truncated>
                <difficult>0</difficult>
                <bndbox>
                        <xmin>447</xmin>
                        <ymin>379</ymin>
                        <xmax>585</xmax>
                        <ymax>455</ymax>
                </bndbox>
        </object>
 <object>
                <name>4s</name>
                <pose>Unspecified</pose>
                <truncated>0</truncated>
                <difficult>0</difficult>
                <bndbox>
                        <xmin>221</xmin>
                        <ymin>492</ymin>
                        <xmax>357</xmax>
                        <ymax>568</ymax>
                </bndbox>
        </object>
</annotation>        
