<annotation>
        <folder>FOLDER</folder>
        <filename>329861293.jpg</filename>
        <path>data/scenes/val/329861293.jpg</path>
        <source>
                <database>Unknown</database>
        </source>
        <size>
                <width>720</width>
                <height>720</height>
                <depth>3</depth>
        </size>
 <object>
                <name>7s</name>
                <pose>Unspecified</pose>
                <truncated>0</truncated>
                <difficult>0</difficult>
                <bndbox>
                        <xmin>410</xmin>
                        <ymin>286</ymin>
                        <xmax>459</xmax>
                        <ymax>384</ymax>
                </bndbox>
        </object>
 <object>
                <name>4d</name>
                <pose>Unspecified</pose>
                <truncated>0</truncated>
                <difficult>0</difficult>
                <bndbox>
                        <xmin>321</xmin>
                        <ymin>252</ymin>
                        <xmax>383</xmax>
                        <ymax>333</ymax>
                </bndbox>
        </object>
 <object>
                <name>4d</name>
                <pose>Unspecified</pose>
                <truncated>0</truncated>
                <difficult>0</difficult>
                <bndbox>
                        <xmin>293</xmin>
                        <ymin>92</ymin>
                        <xmax>355</xmax>
                        <ymax>171</ymax>
                </bndbox>
        </object>
</annotation>        
