<annotation>
        <folder>FOLDER</folder>
        <filename>332536961.jpg</filename>
        <path>data/scenes/val/332536961.jpg</path>
        <source>
                <database>Unknown</database>
        </source>
        <size>
                <width>720</width>
                <height>720</height>
                <depth>3</depth>
        </size>
 <object>
                <name>2d</name>
                <pose>Unspecified</pose>
                <truncated>0</truncated>
                <difficult>0</difficult>
                <bndbox>
                        <xmin>565</xmin>
                        <ymin>486</ymin>
                        <xmax>617</xmax>
                        <ymax>630</ymax>
                </bndbox>
        </object>
 <object>
                <name>Ad</name>
                <pose>Unspecified</pose>
                <truncated>0</truncated>
                <difficult>0</difficult>
                <bndbox>
                        <xmin>512</xmin>
                        <ymin>470</ymin>
                        <xmax>573</xmax>
                        <ymax>612</ymax>
                </bndbox>
        </object>
 <object>
                <name>6h</name>
                <pose>Unspecified</pose>
                <truncated>0</truncated>
                <difficult>0</difficult>
                <bndbox>
                        <xmin>421</xmin>
                        <ymin>449</ymin>
                        <xmax>503</xmax>
                        <ymax>581</ymax>
                </bndbox>
        </object>
 <object>
                <name>6h</name>
                <pose>Unspecified</pose>
                <truncated>0</truncated>
                <difficult>0</difficult>
                <bndbox>
                        <xmin>350</xmin>
                        <ymin>206</ymin>
                        <xmax>433</xmax>
                        <ymax>334</ymax>
                </bndbox>
        </object>
</annotation>        
