<annotation>
        <folder>FOLDER</folder>
        <filename>357286565.jpg</filename>
        <path>data/scenes/val/357286565.jpg</path>
        <source>
                <database>Unknown</database>
        </source>
        <size>
                <width>720</width>
                <height>720</height>
                <depth>3</depth>
        </size>
 <object>
                <name>Jh</name>
                <pose>Unspecified</pose>
                <truncated>0</truncated>
                <difficult>0</difficult>
                <bndbox>
                        <xmin>345</xmin>
                        <ymin>125</ymin>
                        <xmax>435</xmax>
                        <ymax>176</ymax>
                </bndbox>
        </object>
 <object>
                <name>5d</name>
                <pose>Unspecified</pose>
                <truncated>0</truncated>
                <difficult>0</difficult>
                <bndbox>
                        <xmin>353</xmin>
                        <ymin>169</ymin>
                        <xmax>449</xmax>
                        <ymax>219</ymax>
                </bndbox>
        </object>
 <object>
                <name>4h</name>
                <pose>Unspecified</pose>
                <truncated>0</truncated>
                <difficult>0</difficult>
                <bndbox>
                        <xmin>350</xmin>
                        <ymin>227</ymin>
                        <xmax>443</xmax>
                        <ymax>263</ymax>
                </bndbox>
        </object>
 <object>
                <name>4h</name>
                <pose>Unspecified</pose>
                <truncated>0</truncated>
                <difficult>0</difficult>
                <bndbox>
                        <xmin>229</xmin>
                        <ymin>343</ymin>
                        <xmax>321</xmax>
                        <ymax>377</ymax>
                </bndbox>
        </object>
</annotation>        
