<annotation>
        <folder>FOLDER</folder>
        <filename>524234386.jpg</filename>
        <path>data/scenes/val/524234386.jpg</path>
        <source>
                <database>Unknown</database>
        </source>
        <size>
                <width>720</width>
                <height>720</height>
                <depth>3</depth>
        </size>
 <object>
                <name>6d</name>
                <pose>Unspecified</pose>
                <truncated>0</truncated>
                <difficult>0</difficult>
                <bndbox>
                        <xmin>205</xmin>
                        <ymin>563</ymin>
                        <xmax>290</xmax>
                        <ymax>698</ymax>
                </bndbox>
        </object>
 <object>
                <name>6d</name>
                <pose>Unspecified</pose>
                <truncated>0</truncated>
                <difficult>0</difficult>
                <bndbox>
                        <xmin>127</xmin>
                        <ymin>320</ymin>
                        <xmax>211</xmax>
                        <ymax>452</ymax>
                </bndbox>
        </object>
 <object>
                <name>3d</name>
                <pose>Unspecified</pose>
                <truncated>0</truncated>
                <difficult>0</difficult>
                <bndbox>
                        <xmin>507</xmin>
                        <ymin>165</ymin>
                        <xmax>601</xmax>
                        <ymax>221</ymax>
                </bndbox>
        </object>
 <object>
                <name>3d</name>
                <pose>Unspecified</pose>
                <truncated>0</truncated>
                <difficult>0</difficult>
                <bndbox>
                        <xmin>430</xmin>
                        <ymin>320</ymin>
                        <xmax>523</xmax>
                        <ymax>375</ymax>
                </bndbox>
        </object>
</annotation>        
