<annotation>
        <folder>FOLDER</folder>
        <filename>685689193.jpg</filename>
        <path>data/scenes/val/685689193.jpg</path>
        <source>
                <database>Unknown</database>
        </source>
        <size>
                <width>720</width>
                <height>720</height>
                <depth>3</depth>
        </size>
 <object>
                <name>8s</name>
                <pose>Unspecified</pose>
                <truncated>0</truncated>
                <difficult>0</difficult>
                <bndbox>
                        <xmin>288</xmin>
                        <ymin>426</ymin>
                        <xmax>358</xmax>
                        <ymax>514</ymax>
                </bndbox>
        </object>
 <object>
                <name>8s</name>
                <pose>Unspecified</pose>
                <truncated>0</truncated>
                <difficult>0</difficult>
                <bndbox>
                        <xmin>125</xmin>
                        <ymin>389</ymin>
                        <xmax>193</xmax>
                        <ymax>477</ymax>
                </bndbox>
        </object>
 <object>
                <name>8s</name>
                <pose>Unspecified</pose>
                <truncated>0</truncated>
                <difficult>0</difficult>
                <bndbox>
                        <xmin>394</xmin>
                        <ymin>288</ymin>
                        <xmax>490</xmax>
                        <ymax>329</ymax>
                </bndbox>
        </object>
 <object>
                <name>8s</name>
                <pose>Unspecified</pose>
                <truncated>0</truncated>
                <difficult>0</difficult>
                <bndbox>
                        <xmin>528</xmin>
                        <ymin>187</ymin>
                        <xmax>623</xmax>
                        <ymax>229</ymax>
                </bndbox>
        </object>
</annotation>        
