<annotation>
        <folder>FOLDER</folder>
        <filename>810150095.jpg</filename>
        <path>data/scenes/val/810150095.jpg</path>
        <source>
                <database>Unknown</database>
        </source>
        <size>
                <width>720</width>
                <height>720</height>
                <depth>3</depth>
        </size>
 <object>
                <name>9h</name>
                <pose>Unspecified</pose>
                <truncated>0</truncated>
                <difficult>0</difficult>
                <bndbox>
                        <xmin>335</xmin>
                        <ymin>189</ymin>
                        <xmax>451</xmax>
                        <ymax>288</ymax>
                </bndbox>
        </object>
 <object>
                <name>JK</name>
                <pose>Unspecified</pose>
                <truncated>0</truncated>
                <difficult>0</difficult>
                <bndbox>
                        <xmin>458</xmin>
                        <ymin>371</ymin>
                        <xmax>531</xmax>
                        <ymax>421</ymax>
                </bndbox>
        </object>
 <object>
                <name>JK</name>
                <pose>Unspecified</pose>
                <truncated>0</truncated>
                <difficult>0</difficult>
                <bndbox>
                        <xmin>289</xmin>
                        <ymin>602</ymin>
                        <xmax>383</xmax>
                        <ymax>663</ymax>
                </bndbox>
        </object>
</annotation>        
