<annotation>
        <folder>FOLDER</folder>
        <filename>882028120.jpg</filename>
        <path>data/scenes/val/882028120.jpg</path>
        <source>
                <database>Unknown</database>
        </source>
        <size>
                <width>720</width>
                <height>720</height>
                <depth>3</depth>
        </size>
 <object>
                <name>Ad</name>
                <pose>Unspecified</pose>
                <truncated>0</truncated>
                <difficult>0</difficult>
                <bndbox>
                        <xmin>408</xmin>
                        <ymin>373</ymin>
                        <xmax>533</xmax>
                        <ymax>459</ymax>
                </bndbox>
        </object>
 <object>
                <name>Ad</name>
                <pose>Unspecified</pose>
                <truncated>0</truncated>
                <difficult>0</difficult>
                <bndbox>
                        <xmin>480</xmin>
                        <ymin>127</ymin>
                        <xmax>604</xmax>
                        <ymax>210</ymax>
                </bndbox>
        </object>
 <object>
                <name>6s</name>
                <pose>Unspecified</pose>
                <truncated>0</truncated>
                <difficult>0</difficult>
                <bndbox>
                        <xmin>162</xmin>
                        <ymin>157</ymin>
                        <xmax>248</xmax>
                        <ymax>227</ymax>
                </bndbox>
        </object>
 <object>
                <name>6s</name>
                <pose>Unspecified</pose>
                <truncated>0</truncated>
                <difficult>0</difficult>
                <bndbox>
                        <xmin>130</xmin>
                        <ymin>322</ymin>
                        <xmax>216</xmax>
                        <ymax>390</ymax>
                </bndbox>
        </object>
</annotation>        
