<annotation>
        <folder>FOLDER</folder>
        <filename>919181909.jpg</filename>
        <path>data/scenes/val/919181909.jpg</path>
        <source>
                <database>Unknown</database>
        </source>
        <size>
                <width>720</width>
                <height>720</height>
                <depth>3</depth>
        </size>
 <object>
                <name>Kc</name>
                <pose>Unspecified</pose>
                <truncated>0</truncated>
                <difficult>0</difficult>
                <bndbox>
                        <xmin>257</xmin>
                        <ymin>118</ymin>
                        <xmax>296</xmax>
                        <ymax>212</ymax>
                </bndbox>
        </object>
 <object>
                <name>6h</name>
                <pose>Unspecified</pose>
                <truncated>0</truncated>
                <difficult>0</difficult>
                <bndbox>
                        <xmin>294</xmin>
                        <ymin>123</ymin>
                        <xmax>338</xmax>
                        <ymax>215</ymax>
                </bndbox>
        </object>
 <object>
                <name>7c</name>
                <pose>Unspecified</pose>
                <truncated>0</truncated>
                <difficult>0</difficult>
                <bndbox>
                        <xmin>335</xmin>
                        <ymin>153</ymin>
                        <xmax>402</xmax>
                        <ymax>245</ymax>
                </bndbox>
        </object>
 <object>
                <name>7c</name>
                <pose>Unspecified</pose>
                <truncated>0</truncated>
                <difficult>0</difficult>
                <bndbox>
                        <xmin>378</xmin>
                        <ymin>321</ymin>
                        <xmax>445</xmax>
                        <ymax>411</ymax>
                </bndbox>
        </object>
</annotation>        
