<annotation>
        <folder>FOLDER</folder>
        <filename>964963470.jpg</filename>
        <path>data/scenes/val/964963470.jpg</path>
        <source>
                <database>Unknown</database>
        </source>
        <size>
                <width>720</width>
                <height>720</height>
                <depth>3</depth>
        </size>
 <object>
                <name>4d</name>
                <pose>Unspecified</pose>
                <truncated>0</truncated>
                <difficult>0</difficult>
                <bndbox>
                        <xmin>349</xmin>
                        <ymin>349</ymin>
                        <xmax>424</xmax>
                        <ymax>417</ymax>
                </bndbox>
        </object>
 <object>
                <name>4d</name>
                <pose>Unspecified</pose>
                <truncated>0</truncated>
                <difficult>0</difficult>
                <bndbox>
                        <xmin>513</xmin>
                        <ymin>339</ymin>
                        <xmax>587</xmax>
                        <ymax>407</ymax>
                </bndbox>
        </object>
 <object>
                <name>5c</name>
                <pose>Unspecified</pose>
                <truncated>0</truncated>
                <difficult>0</difficult>
                <bndbox>
                        <xmin>303</xmin>
                        <ymin>477</ymin>
                        <xmax>341</xmax>
                        <ymax>571</ymax>
                </bndbox>
        </object>
 <object>
                <name>5c</name>
                <pose>Unspecified</pose>
                <truncated>0</truncated>
                <difficult>0</difficult>
                <bndbox>
                        <xmin>183</xmin>
                        <ymin>360</ymin>
                        <xmax>221</xmax>
                        <ymax>453</ymax>
                </bndbox>
        </object>
</annotation>        
